ttask/__init__.py
ttask/main.py
ttask/todotxtio.py
ttask-0.1.5.dist-info/entry_points.txt
ttask-0.1.5.dist-info/LICENSE
ttask-0.1.5.dist-info/WHEEL
ttask-0.1.5.dist-info/METADATA
ttask-0.1.5.dist-info/RECORD
