Metadata-Version: 2.1
Name: ttask
Version: 0.1.5
Summary: 
Home-page: https://github.com/sleepntsheep/ttask
License: MIT
Author: sleepntsheep
Author-email: contact@papangkorn.com
Requires-Python: >=3.5
Classifier: License :: OSI Approved :: MIT License
Classifier: Programming Language :: Python :: 3
Classifier: Programming Language :: Python :: 3.5
Classifier: Programming Language :: Python :: 3.6
Classifier: Programming Language :: Python :: 3.7
Classifier: Programming Language :: Python :: 3.8
Classifier: Programming Language :: Python :: 3.9
Requires-Dist: windows-curses (>=2.2.0,<3.0.0); sys_platform == "win32"
Project-URL: Repository, https://github.com/sleepntsheep/ttask
